{"_id":"note:0-mtMJdZt","title":"JS DOM Basics","content":"## Blog refernce\n\nhttps://blog.garstasio.com/you-dont-need-jquery/dom-manipulation/\n\n\n### Math.random()\n\nIt generates a value in between 0 & 1 , but not 0 or 1.\n\nso if you want to generate a number between 1-6\n\n```js\ndice = Math.floor(Math.random() * 6) + 1\nconsole.log(dice)\n```\n\n## Query Selector (DOM Manipulation)\n\ntextContent : is used to modify the plain text\n\ninnerHTML: is used to modify the HTML\n \n### using as Setter\n ```js\n// for ids we use # prefix\n// for class we use . prefix\ndocument.querySelector('#current-0').textContent = dice\n\n\ndocument.querySelector('#current-0').innerHTML = '<em>'+dice+'<em>'\n\n// change style..\ndocument.querySelector('.dice').style.display = 'none';\n```\n\n### using as getter\n\n```js\nvar x = document.querySelector('#score-' + activePlayer).textContent\nconsole.log(x)\n```\n\n## Events & Event Listeners\n\nEvents -> click,dblclick, mouseup ...  check MDN for more\n\nEvent Listeners -> are stored in message queue, and initally the function are cleared from execution stack, and only loaded when event is executed.\n\ncallback fns -> fns that are called by otherfn like here event listener is calling the function.\n\nToggle is used when condition is like add if does not exist otherwise remove.    similary you can use ``.add('active')  or .remove('active)``\n\n``          document.querySelector('.player-0-panel').classList.toggle('active')``\n\n\nSample Code\n```js\n\n// here the function is also called anonymous function\ndocument.querySelector('.btn-roll').addEventListener('click',function()\n{\n    dice = Math.floor(Math.random() * 6) + 1\n    \n    var diceDOM = document.querySelector('.dice')\n    //modify the style\n    diceDOM.style.display = 'block'\n    \n    // modfiy HTML attributes\n    diceDOM.src = 'dice-'+ dice + '.png'\n          \n          document.querySelector('.player-0-panel').classList.toggle('active')\n          document.querySelector('.player-1-panel').classList.toggle('active')\n          \n          document.querySelector('.dice').style.display = 'none'\n    }\n})\n```","tags":[],"folderPathname":"/","data":{},"createdAt":"2020-10-06T15:05:20.184Z","updatedAt":"2020-10-12T13:17:02.554Z","trashed":false,"_rev":"BE6I-gzH8"}